csi_utils/__init__.py
csi_utils/csi_communication.py
csi_utils/csi_data_preprocess.py
csi_utils/csi_storage.py
csi_utils/test.py
csi_utils-0.0.35.dist-info/LICENSE
csi_utils-0.0.35.dist-info/METADATA
csi_utils-0.0.35.dist-info/WHEEL
csi_utils-0.0.35.dist-info/top_level.txt
csi_utils-0.0.35.dist-info/RECORD
