Metadata-Version: 2.1
Name: csi-utils
Version: 0.0.35
Summary: utils for Wifi CSI data process
Home-page: https://github.com/ykoneee/
Author: ykone
Author-email: 245403188gm@gmail.com
License: UNKNOWN
Platform: UNKNOWN
Classifier: License :: OSI Approved :: MIT License
Classifier: Operating System :: OS Independent
Requires-Python: >=3.5, <4
Requires-Dist: pyzmq
Requires-Dist: numpy
Requires-Dist: zarr
Requires-Dist: h5py
Requires-Dist: numcodecs
